setup.py
android_tool.egg-info/PKG-INFO
android_tool.egg-info/SOURCES.txt
android_tool.egg-info/dependency_links.txt
android_tool.egg-info/top_level.txt
androidtool/__init__.py
androidtool/android_tool.py