Metadata-Version: 1.0
Name: android-tool
Version: 1.1.2
Summary: Script which aids you in few Android development practises
Home-page: https://github.com/MrRobot9/android-tool
Author: Arjun Gurudatta Hegde
Author-email: arjunhegde777@gmail.com
License: MIT
Keywords: android-tool,localization
Platform: UNKNOWN
